COPYING
ChangeLog
MANIFEST.in
NEWS
README
THANKS
liblzma.c
liblzma.h
liblzma.py
liblzma_compressobj.c
liblzma_compressobj.h
liblzma_decompressobj.c
liblzma_decompressobj.h
liblzma_file.c
liblzma_file.h
liblzma_fileobj.c
liblzma_fileobj.h
liblzma_options.c
liblzma_options.h
liblzma_util.c
liblzma_util.h
python-liblzma.spec
setup.cfg
setup.py
pyliblzma.egg-info/PKG-INFO
pyliblzma.egg-info/SOURCES.txt
pyliblzma.egg-info/dependency_links.txt
pyliblzma.egg-info/top_level.txt
tests/__init__.py
tests/regrtest.py
tests/test_liblzma.py
tests/data/teststring.lzma
tests/data/teststring.xz