Metadata-Version: 1.0
Name: pyliblzma
Version: 0.5.2
Summary: Python bindings for liblzma
Home-page: https://launchpad.net/pyliblzma
Author: Per Øyvind Karlsen
Author-email: peroyvind@mandriva.org
License: LGPL 3 
Keywords: xz lzma compression
Platform: linux2
Classifier: Development Status :: 4 - Beta
Classifier: Programming Language :: Python
Classifier: Topic :: Software Development :: Libraries :: Python Modules
Classifier: Intended Audience :: Developers
Classifier: License :: OSI Approved :: GNU Library or Lesser General Public License (LGPL)
Classifier: Operating System :: POSIX :: Linux
